bundlewrap/__init__.py
bundlewrap/bundle.py
bundlewrap/concurrency.py
bundlewrap/deps.py
bundlewrap/exceptions.py
bundlewrap/group.py
bundlewrap/itemqueue.py
bundlewrap/lock.py
bundlewrap/metadata.py
bundlewrap/metagen.py
bundlewrap/node.py
bundlewrap/operations.py
bundlewrap/repo.py
bundlewrap/secrets.py
bundlewrap/cmdline/__init__.py
bundlewrap/cmdline/apply.py
bundlewrap/cmdline/debug.py
bundlewrap/cmdline/diff.py
bundlewrap/cmdline/generate_completions.py
bundlewrap/cmdline/groups.py
bundlewrap/cmdline/hash.py
bundlewrap/cmdline/ipmi.py
bundlewrap/cmdline/items.py
bundlewrap/cmdline/lock.py
bundlewrap/cmdline/metadata.py
bundlewrap/cmdline/nodes.py
bundlewrap/cmdline/parser.py
bundlewrap/cmdline/plot.py
bundlewrap/cmdline/pw.py
bundlewrap/cmdline/repo.py
bundlewrap/cmdline/run.py
bundlewrap/cmdline/stats.py
bundlewrap/cmdline/test.py
bundlewrap/cmdline/verify.py
bundlewrap/cmdline/zen.py
bundlewrap/items/__init__.py
bundlewrap/items/actions.py
bundlewrap/items/dconf.py
bundlewrap/items/directories.py
bundlewrap/items/files.py
bundlewrap/items/git_deploy.py
bundlewrap/items/groups.py
bundlewrap/items/kubernetes.py
bundlewrap/items/pkg.py
bundlewrap/items/pkg_apk.py
bundlewrap/items/pkg_apt.py
bundlewrap/items/pkg_dnf.py
bundlewrap/items/pkg_freebsd.py
bundlewrap/items/pkg_openbsd.py
bundlewrap/items/pkg_opkg.py
bundlewrap/items/pkg_pacman.py
bundlewrap/items/pkg_pamac.py
bundlewrap/items/pkg_pip.py
bundlewrap/items/pkg_snap.py
bundlewrap/items/pkg_yum.py
bundlewrap/items/pkg_zypper.py
bundlewrap/items/postgres_dbs.py
bundlewrap/items/postgres_roles.py
bundlewrap/items/routeros.py
bundlewrap/items/svc_freebsd.py
bundlewrap/items/svc_openbsd.py
bundlewrap/items/svc_openrc.py
bundlewrap/items/svc_systemd.py
bundlewrap/items/svc_systemv.py
bundlewrap/items/symlinks.py
bundlewrap/items/users.py
bundlewrap/items/zfs_dataset.py
bundlewrap/items/zfs_pool.py
bundlewrap/utils/__init__.py
bundlewrap/utils/cmdline.py
bundlewrap/utils/crypto.py
bundlewrap/utils/dicts.py
bundlewrap-5.0.0.dist-info/licenses/AUTHORS
bundlewrap-5.0.0.dist-info/licenses/LICENSE
bundlewrap-5.0.0.dist-info/METADATA
bundlewrap-5.0.0.dist-info/WHEEL
bundlewrap-5.0.0.dist-info/entry_points.txt
bundlewrap-5.0.0.dist-info/top_level.txt
bundlewrap-5.0.0.dist-info/RECORD
