Metadata-Version: 2.4
Name: bundlewrap
Version: 5.0.0
Summary: Config management with Python
Home-page: http://bundlewrap.org
Author: Torsten Rehn
Author-email: torsten@rehn.email
License: GPLv3
Keywords: configuration,config,management
Classifier: Development Status :: 5 - Production/Stable
Classifier: Environment :: Console
Classifier: Intended Audience :: System Administrators
Classifier: License :: OSI Approved :: GNU General Public License v3 (GPLv3)
Classifier: Natural Language :: English
Classifier: Operating System :: POSIX :: Linux
Classifier: Programming Language :: Python
Classifier: Programming Language :: Python :: 3.10
Classifier: Programming Language :: Python :: 3.11
Classifier: Programming Language :: Python :: 3.12
Classifier: Programming Language :: Python :: 3.13
Classifier: Programming Language :: Python :: 3.14
Classifier: Topic :: System :: Installation/Setup
Classifier: Topic :: System :: Systems Administration
License-File: LICENSE
License-File: AUTHORS
Requires-Dist: bcrypt
Requires-Dist: cryptography
Requires-Dist: Jinja2
Requires-Dist: librouteros>=3.0.0
Requires-Dist: Mako
Requires-Dist: packaging>=25; python_version >= "3.10"
Requires-Dist: pyyaml
Requires-Dist: requests>=1.0.0
Requires-Dist: rtoml; python_version < "3.11"
Requires-Dist: setuptools<=80.8.0; python_version < "3.10"
Requires-Dist: tomlkit
Dynamic: author
Dynamic: author-email
Dynamic: classifier
Dynamic: description
Dynamic: home-page
Dynamic: keywords
Dynamic: license
Dynamic: license-file
Dynamic: requires-dist
Dynamic: summary
